colt/__init__.py
colt/_compat.py
colt/_constants.py
colt/builder.py
colt/callback.py
colt/context.py
colt/default_registry.py
colt/error.py
colt/jsonschema.py
colt/lazy.py
colt/placeholder.py
colt/py.typed
colt/registrable.py
colt/types.py
colt/utils.py
colt-0.18.1.dist-info/WHEEL
colt-0.18.1.dist-info/METADATA
colt-0.18.1.dist-info/RECORD
