Metadata-Version: 2.4
Name: colt
Version: 0.18.1
Summary: A configuration utility for Python object.
Keywords: config,python,object
Author: altescy
Author-email: altescy <me@altescy.jp>
License-Expression: MIT
Classifier: License :: OSI Approved :: MIT License
Classifier: Development Status :: 3 - Alpha
Classifier: Programming Language :: Python :: 3.8
Classifier: Programming Language :: Python :: 3.9
Classifier: Programming Language :: Python :: 3.10
Classifier: Programming Language :: Python :: 3.11
Classifier: Programming Language :: Python :: 3.12
Classifier: Programming Language :: Python :: 3.13
Requires-Python: >=3.8, <4.0
Project-URL: HomePage, https://github.com/altescy/colt
Project-URL: Issues, https://github.com/altescy/colt/issues
